{"type": "Feature", "id": 12515025, "geometry": {"type": "Point", "coordinates": [35.0411, -17.3703]}, "properties": {"woe:id": 12515025, "woe:parent_id": 1553656, "woe:name": "Mutarara Airport", "woe:placetype": 14, "woe:placetype_name": "Airport", "woe:lang": "ENG", "iso:country": "MZ", "meta:provider": ["geoplanet:7.3.1", "geoplanet:7.3.2", "geoplanet:7.4.0", "geoplanet:7.4.1", "geoplanet:7.5.1", "geoplanet:7.5.2", "geoplanet:7.6.0", "geoplanet:7.8.1", "geoplanet:7.9.0", "geoplanet:7.10.0", "geoplanet:8.0.0", "woeplanet:8.0.0"], "meta:indexed": "2020-08-20T20:26:59.583193", "meta:updated": "2020-10-14T11:29:26.564404", "woe:hierarchy": {"continent": 24865670, "country": 23424902, "town": 0, "planet": 1, "county": 0, "suburb": 0, "state": 2346318, "region": 0, "localadmin": 0}, "woe:timezone_id": 28350716, "woe:hash": "kubvjmu4sv3u", "woe:centroid": [35.0411, -17.3703], "geom:latitude": -17.3703, "geom:longitude": 35.0411, "geom:hash": "kubvjmu4sv3u", "woe:latitude": -17.3703, "geom:centroid": [35.0411, -17.3703], "woe:longitude": 35.0411, "woe:repo": "woeplanet-airport-mz", "geom:area": 0.0, "woe:scale": 19}}